alibabacloud_sts20150401/__init__.py
alibabacloud_sts20150401/client.py
alibabacloud_sts20150401/models/__init__.py
alibabacloud_sts20150401/models/_assume_role_request.py
alibabacloud_sts20150401/models/_assume_role_response.py
alibabacloud_sts20150401/models/_assume_role_response_body.py
alibabacloud_sts20150401/models/_assume_role_with_oidcrequest.py
alibabacloud_sts20150401/models/_assume_role_with_oidcresponse.py
alibabacloud_sts20150401/models/_assume_role_with_oidcresponse_body.py
alibabacloud_sts20150401/models/_assume_role_with_samlrequest.py
alibabacloud_sts20150401/models/_assume_role_with_samlresponse.py
alibabacloud_sts20150401/models/_assume_role_with_samlresponse_body.py
alibabacloud_sts20150401/models/_get_caller_identity_response.py
alibabacloud_sts20150401/models/_get_caller_identity_response_body.py
alibabacloud_sts20150401-1.2.0.dist-info/LICENSE
alibabacloud_sts20150401-1.2.0.dist-info/METADATA
alibabacloud_sts20150401-1.2.0.dist-info/WHEEL
alibabacloud_sts20150401-1.2.0.dist-info/top_level.txt
alibabacloud_sts20150401-1.2.0.dist-info/RECORD
